MANIFEST.in
Makefile
README.md
ransac.py
setup.py
c/exterior_algebra.c
c/fail.c
c/homographies.c
c/moistiv_epipolar.c
c/parsenumbers.c
c/random.c
c/ransac.c
c/ransac_cases.c
c/vvector.h
c/xfopen.c
c/xmalloc.c
ransac.egg-info/PKG-INFO
ransac.egg-info/SOURCES.txt
ransac.egg-info/dependency_links.txt
ransac.egg-info/requires.txt
ransac.egg-info/top_level.txt