Metadata-Version: 2.1
Name: ransac
Version: 1.0.3
Summary: Python wrapper of Enric Meinhardt's RANSAC implementation
Home-page: https://github.com/cmla/ransac
Author: Carlo de Franchis
Author-email: carlo.de-franchis@ens-cachan.fr
License: UNKNOWN
Platform: UNKNOWN
Provides-Extra: test
